Aggregator/Aggregator.py
Aggregator/__init__.py
Aggregator-20.5.dist-info/LICENSE.txt
Aggregator-20.5.dist-info/METADATA
Aggregator-20.5.dist-info/WHEEL
Aggregator-20.5.dist-info/top_level.txt
Aggregator-20.5.dist-info/RECORD
